pydantic_file_secrets/__init__.py
pydantic_file_secrets/__version__.py
pydantic_file_secrets/customise.py
pydantic_file_secrets/py.typed
pydantic_file_secrets/types.py
pydantic_file_secrets-0.4.4.dist-info/METADATA
pydantic_file_secrets-0.4.4.dist-info/WHEEL
pydantic_file_secrets-0.4.4.dist-info/licenses/LICENSE
pydantic_file_secrets-0.4.4.dist-info/RECORD
