Metadata-Version: 2.4
Name: pydantic-file-secrets
Version: 0.4.4
Summary: Use file secrets in nested pydantic-settings models instead of built-in SecretsSettingsSource
Project-URL: Documentation, https://github.com/makukha/pydantic-file-secrets#readme
Project-URL: Homepage, https://github.com/makukha/pydantic-file-secrets
Project-URL: Repository, https://github.com/makukha/pydantic-file-secrets
Project-URL: Issues, https://github.com/makukha/pydantic-file-secrets/issues
Project-URL: Changelog, https://github.com/makukha/pydantic-file-secrets/blob/main/CHANGELOG.md
Author-email: Michael Makukha <m.makukha@gmail.com>
License: MIT
License-File: LICENSE
Keywords: config,configuration,docker,docker-secret,file-secrets,pydantic,pydantic-settings,pydantic-v2,python,python3,secrets,settings,validation
Classifier: Development Status :: 4 - Beta
Classifier: Framework :: Pydantic
Classifier: Framework :: Pydantic :: 2
Classifier: Intended Audience :: Developers
Classifier: License :: OSI Approved :: MIT License
Classifier: Operating System :: OS Independent
Classifier: Programming Language :: Python
Classifier: Programming Language :: Python :: 3.8
Classifier: Programming Language :: Python :: 3.9
Classifier: Programming Language :: Python :: 3.10
Classifier: Programming Language :: Python :: 3.11
Classifier: Programming Language :: Python :: 3.12
Classifier: Programming Language :: Python :: 3.13
Classifier: Programming Language :: Python :: Implementation :: CPython
Classifier: Topic :: Software Development
Classifier: Typing :: Typed
Requires-Python: >=3.8
Requires-Dist: pydantic-settings<3,>=2.2
Requires-Dist: typing-extensions>=4
